bento_sgl_router-0.0.6.dist-info/METADATA
bento_sgl_router-0.0.6.dist-info/WHEEL
bento_sgl_router-0.0.6.dist-info/entry_points.txt
bento_sgl_router.py
bento_sgl_router-0.0.6.dist-info/RECORD
