Metadata-Version: 2.1
Name: bento-sgl-router
Version: 0.0.6
Summary: Bento service with SGLang Router included
Author-Email: Frost Ming <frost@bentoml.com>
License: MIT
Requires-Python: >=3.10
Requires-Dist: bentoml>=1.4.25
Requires-Dist: sglang-router>=0.1.9
